pyummeter/__init__.py
pyummeter/export_csv.py
pyummeter/interface_base.py
pyummeter/interface_tty.py
pyummeter/ummeter.py
pyummeter-0.2.0.dist-info/WHEEL
pyummeter-0.2.0.dist-info/METADATA
pyummeter-0.2.0.dist-info/RECORD
