Metadata-Version: 2.1
Name: pyummeter
Version: 0.2.0
Summary: Python UM-Meter interface
Home-page: https://github.com/valletw/pyummeter
License: MIT
Keywords: ummeter
Author: William Vallet
Author-email: valletw@gmail.com
Requires-Python: >=3.8,<4.0
Classifier: License :: OSI Approved :: MIT License
Classifier: Programming Language :: Python :: 3
Classifier: Programming Language :: Python :: 3.8
Classifier: Programming Language :: Python :: 3.9
Classifier: Programming Language :: Python :: 3.10
Classifier: Programming Language :: Python :: 3.11
Requires-Dist: pyserial (>=3.5,<4.0)
Project-URL: Repository, https://github.com/valletw/pyummeter
